cuteprint/cuteprint.py
cuteprint-0.1.1.dist-info/LICENSE.txt
cuteprint-0.1.1.dist-info/METADATA
cuteprint-0.1.1.dist-info/WHEEL
cuteprint-0.1.1.dist-info/top_level.txt
cuteprint-0.1.1.dist-info/RECORD
