Metadata-Version: 2.1
Name: cuteprint
Version: 0.1.1
Summary: A Pretty Print Utils Library
Home-page: https://github.com/terryvogelsang/cuteprint
Author: Terry Vogelsang
Author-email: terry.vogelsang@protonmail.com
License: UNKNOWN
Download-URL: https://github.com/terryvogelsang/cuteprint/archive/0.1.1.tar.gz
Keywords: pretty,print,cute
Platform: UNKNOWN
